zbr/__init__.py
zbr/__main__.py
zbr-0.1a0.dist-info/LICENSE
zbr-0.1a0.dist-info/METADATA
zbr-0.1a0.dist-info/WHEEL
zbr-0.1a0.dist-info/entry_points.txt
zbr-0.1a0.dist-info/top_level.txt
zbr-0.1a0.dist-info/RECORD
